{"sentences":[{"end":13,"begin":0},{"end":200,"begin":16},{"end":328,"begin":201},{"end":378,"begin":329},{"end":574,"begin":379},{"end":705,"begin":577},{"end":816,"begin":706},{"end":891,"begin":817},{"end":1008,"begin":892},{"end":1103,"begin":1009},{"end":1308,"begin":1104},{"end":1352,"begin":1311},{"end":1514,"begin":1353},{"end":1636,"begin":1515},{"end":1707,"begin":1637},{"end":1866,"begin":1708},{"end":2049,"begin":1867},{"end":2134,"begin":2050},{"end":2266,"begin":2135}],"tokens":[{"end":6,"begin":0},{"end":13,"begin":7},{"end":19,"begin":16},{"end":27,"begin":20},{"end":38,"begin":28},{"end":45,"begin":39},{"end":55,"begin":46},{"end":60,"begin":56},{"end":65,"begin":61},{"end":69,"begin":66},{"end":70,"begin":69},{"end":74,"begin":71},{"end":77,"begin":75},{"end":83,"begin":78},{"end":88,"begin":84},{"end":93,"begin":89},{"end":96,"begin":95},{"end":102,"begin":96},{"end":107,"begin":103},{"end":113,"begin":108},{"end":114,"begin":113},{"end":119,"begin":116},{"end":123,"begin":120},{"end":130,"begin":124},{"end":133,"begin":131},{"end":140,"begin":134},{"end":144,"begin":141},{"end":150,"begin":145},{"end":154,"begin":151},{"end":162,"begin":155},{"end":168,"begin":163},{"end":189,"begin":169},{"end":192,"begin":190},{"end":199,"begin":193},{"end":200,"begin":199},{"end":204,"begin":201},{"end":209,"begin":205},{"end":215,"begin":210},{"end":224,"begin":216},{"end":228,"begin":225},{"end":233,"begin":229},{"end":237,"begin":234},{"end":240,"begin":238},{"end":251,"begin":241},{"end":255,"begin":252},{"end":258,"begin":256},{"end":266,"begin":259},{"end":275,"begin":267},{"end":281,"begin":276},{"end":294,"begin":282},{"end":295,"begin":294},{"end":299,"begin":296},{"end":303,"begin":300},{"end":317,"begin":304},{"end":327,"begin":318},{"end":328,"begin":327},{"end":332,"begin":329},{"end":342,"begin":333},{"end":349,"begin":343},{"end":353,"begin":350},{"end":359,"begin":354},{"end":362,"begin":360},{"end":366,"begin":363},{"end":371,"begin":367},{"end":377,"begin":372},{"end":378,"begin":377},{"end":381,"begin":379},{"end":385,"begin":382},{"end":397,"begin":386},{"end":407,"begin":398},{"end":414,"begin":408},{"end":415,"begin":414},{"end":419,"begin":416},{"end":425,"begin":420},{"end":435,"begin":426},{"end":440,"begin":436},{"end":450,"begin":441},{"end":459,"begin":451},{"end":475,"begin":460},{"end":476,"begin":475},{"end":484,"begin":477},{"end":488,"begin":485},{"end":493,"begin":489},{"end":496,"begin":494},{"end":516,"begin":497},{"end":524,"begin":517},{"end":526,"begin":525},{"end":529,"begin":526},{"end":532,"begin":530},{"end":533,"begin":532},{"end":537,"begin":534},{"end":548,"begin":538},{"end":550,"begin":549},{"end":552,"begin":550},{"end":555,"begin":553},{"end":556,"begin":555},{"end":560,"begin":557},{"end":564,"begin":561},{"end":568,"begin":565},{"end":573,"begin":569},{"end":574,"begin":573},{"end":587,"begin":577},{"end":593,"begin":588},{"end":596,"begin":594},{"end":600,"begin":597},{"end":606,"begin":601},{"end":610,"begin":607},{"end":618,"begin":611},{"end":623,"begin":619},{"end":632,"begin":624},{"end":636,"begin":633},{"end":647,"begin":637},{"end":653,"begin":648},{"end":660,"begin":654},{"end":663,"begin":661},{"end":668,"begin":664},{"end":672,"begin":669},{"end":680,"begin":673},{"end":691,"begin":681},{"end":704,"begin":692},{"end":705,"begin":704},{"end":709,"begin":706},{"end":715,"begin":710},{"end":728,"begin":716},{"end":732,"begin":729},{"end":746,"begin":733},{"end":749,"begin":748},{"end":754,"begin":749},{"end":761,"begin":755},{"end":762,"begin":761},{"end":767,"begin":764},{"end":775,"begin":768},{"end":776,"begin":775},{"end":785,"begin":777},{"end":800,"begin":786},{"end":815,"begin":801},{"end":816,"begin":815},{"end":819,"begin":817},{"end":823,"begin":820},{"end":831,"begin":824},{"end":835,"begin":832},{"end":842,"begin":836},{"end":850,"begin":843},{"end":854,"begin":851},{"end":858,"begin":855},{"end":870,"begin":859},{"end":880,"begin":871},{"end":885,"begin":881},{"end":890,"begin":886},{"end":891,"begin":890},{"end":895,"begin":892},{"end":900,"begin":896},{"end":901,"begin":900},{"end":905,"begin":902},{"end":910,"begin":906},{"end":914,"begin":911},{"end":917,"begin":915},{"end":926,"begin":918},{"end":929,"begin":927},{"end":935,"begin":930},{"end":939,"begin":936},{"end":940,"begin":939},{"end":946,"begin":941},{"end":952,"begin":947},{"end":959,"begin":953},{"end":969,"begin":960},{"end":980,"begin":970},{"end":988,"begin":981},{"end":997,"begin":989},{"end":1007,"begin":998},{"end":1008,"begin":1007},{"end":1012,"begin":1009},{"end":1025,"begin":1013},{"end":1033,"begin":1026},{"end":1037,"begin":1034},{"end":1043,"begin":1038},{"end":1046,"begin":1044},{"end":1052,"begin":1047},{"end":1059,"begin":1053},{"end":1068,"begin":1060},{"end":1072,"begin":1069},{"end":1084,"begin":1073},{"end":1090,"begin":1085},{"end":1094,"begin":1091},{"end":1102,"begin":1095},{"end":1103,"begin":1102},{"end":1108,"begin":1104},{"end":1116,"begin":1109},{"end":1122,"begin":1117},{"end":1129,"begin":1123},{"end":1133,"begin":1130},{"end":1137,"begin":1134},{"end":1145,"begin":1138},{"end":1148,"begin":1147},{"end":1154,"begin":1148},{"end":1158,"begin":1155},{"end":1166,"begin":1159},{"end":1167,"begin":1166},{"end":1176,"begin":1169},{"end":1177,"begin":1176},{"end":1184,"begin":1178},{"end":1193,"begin":1185},{"end":1197,"begin":1194},{"end":1215,"begin":1198},{"end":1224,"begin":1216},{"end":1228,"begin":1225},{"end":1238,"begin":1229},{"end":1248,"begin":1239},{"end":1254,"begin":1249},{"end":1267,"begin":1255},{"end":1268,"begin":1267},{"end":1276,"begin":1270},{"end":1280,"begin":1277},{"end":1285,"begin":1281},{"end":1290,"begin":1286},{"end":1293,"begin":1292},{"end":1297,"begin":1293},{"end":1305,"begin":1298},{"end":1306,"begin":1305},{"end":1308,"begin":1307},{"end":1314,"begin":1311},{"end":1329,"begin":1315},{"end":1336,"begin":1330},{"end":1343,"begin":1337},{"end":1347,"begin":1344},{"end":1351,"begin":1348},{"end":1352,"begin":1351},{"end":1355,"begin":1353},{"end":1363,"begin":1356},{"end":1367,"begin":1364},{"end":1371,"begin":1368},{"end":1379,"begin":1372},{"end":1380,"begin":1379},{"end":1384,"begin":1381},{"end":1394,"begin":1385},{"end":1398,"begin":1395},{"end":1401,"begin":1400},{"end":1412,"begin":1401},{"end":1426,"begin":1413},{"end":1427,"begin":1426},{"end":1429,"begin":1428},{"end":1433,"begin":1430},{"end":1443,"begin":1434},{"end":1446,"begin":1444},{"end":1453,"begin":1447},{"end":1463,"begin":1454},{"end":1477,"begin":1464},{"end":1478,"begin":1477},{"end":1485,"begin":1479},{"end":1489,"begin":1486},{"end":1502,"begin":1490},{"end":1509,"begin":1503},{"end":1513,"begin":1510},{"end":1514,"begin":1513},{"end":1521,"begin":1515},{"end":1531,"begin":1522},{"end":1542,"begin":1532},{"end":1546,"begin":1543},{"end":1558,"begin":1547},{"end":1559,"begin":1558},{"end":1569,"begin":1560},{"end":1575,"begin":1570},{"end":1578,"begin":1576},{"end":1582,"begin":1579},{"end":1589,"begin":1583},{"end":1593,"begin":1590},{"end":1609,"begin":1594},{"end":1613,"begin":1610},{"end":1616,"begin":1614},{"end":1620,"begin":1617},{"end":1635,"begin":1621},{"end":1636,"begin":1635},{"end":1642,"begin":1637},{"end":1658,"begin":1643},{"end":1662,"begin":1659},{"end":1666,"begin":1663},{"end":1670,"begin":1667},{"end":1676,"begin":1671},{"end":1679,"begin":1677},{"end":1683,"begin":1680},{"end":1687,"begin":1684},{"end":1695,"begin":1688},{"end":1698,"begin":1696},{"end":1702,"begin":1699},{"end":1706,"begin":1703},{"end":1707,"begin":1706},{"end":1715,"begin":1708},{"end":1721,"begin":1716},{"end":1724,"begin":1722},{"end":1728,"begin":1725},{"end":1732,"begin":1729},{"end":1736,"begin":1733},{"end":1751,"begin":1737},{"end":1752,"begin":1751},{"end":1755,"begin":1753},{"end":1761,"begin":1756},{"end":1765,"begin":1762},{"end":1777,"begin":1766},{"end":1787,"begin":1778},{"end":1788,"begin":1787},{"end":1792,"begin":1789},{"end":1796,"begin":1793},{"end":1802,"begin":1797},{"end":1806,"begin":1803},{"end":1822,"begin":1807},{"end":1825,"begin":1823},{"end":1835,"begin":1826},{"end":1854,"begin":1836},{"end":1865,"begin":1855},{"end":1866,"begin":1865},{"end":1874,"begin":1867},{"end":1880,"begin":1875},{"end":1887,"begin":1881},{"end":1893,"begin":1888},{"end":1901,"begin":1894},{"end":1907,"begin":1902},{"end":1911,"begin":1908},{"end":1924,"begin":1912},{"end":1927,"begin":1926},{"end":1935,"begin":1927},{"end":1939,"begin":1936},{"end":1943,"begin":1940},{"end":1951,"begin":1944},{"end":1952,"begin":1951},{"end":1955,"begin":1954},{"end":1959,"begin":1955},{"end":1960,"begin":1959},{"end":1961,"begin":1960},{"end":1964,"begin":1963},{"end":1970,"begin":1964},{"end":1971,"begin":1970},{"end":1975,"begin":1972},{"end":1984,"begin":1976},{"end":1987,"begin":1985},{"end":1994,"begin":1988},{"end":1995,"begin":1994},{"end":1998,"begin":1997},{"end":2002,"begin":1998},{"end":2003,"begin":2002},{"end":2007,"begin":2004},{"end":2010,"begin":2009},{"end":2015,"begin":2010},{"end":2018,"begin":2016},{"end":2022,"begin":2019},{"end":2027,"begin":2023},{"end":2039,"begin":2028},{"end":2040,"begin":2039},{"end":2043,"begin":2042},{"end":2047,"begin":2043},{"end":2048,"begin":2047},{"end":2049,"begin":2048},{"end":2057,"begin":2050},{"end":2067,"begin":2058},{"end":2070,"begin":2068},{"end":2075,"begin":2071},{"end":2079,"begin":2076},{"end":2088,"begin":2080},{"end":2089,"begin":2088},{"end":2100,"begin":2090},{"end":2101,"begin":2100},{"end":2113,"begin":2102},{"end":2117,"begin":2114},{"end":2133,"begin":2118},{"end":2134,"begin":2133},{"end":2141,"begin":2135},{"end":2150,"begin":2142},{"end":2161,"begin":2151},{"end":2164,"begin":2162},{"end":2179,"begin":2165},{"end":2183,"begin":2180},{"end":2187,"begin":2184},{"end":2197,"begin":2188},{"end":2203,"begin":2198},{"end":2210,"begin":2204},{"end":2212,"begin":2211},{"end":2216,"begin":2212},{"end":2220,"begin":2217},{"end":2225,"begin":2221},{"end":2226,"begin":2225},{"end":2227,"begin":2226},{"end":2231,"begin":2228},{"end":2235,"begin":2232},{"end":2238,"begin":2236},{"end":2243,"begin":2239},{"end":2249,"begin":2244},{"end":2261,"begin":2250},{"end":2265,"begin":2262},{"end":2266,"begin":2265}],"text":"Unterm Strich\n\n\nDie private Initiative Aktion Arschloch ruft dazu auf, das 22 Jahre alte Lied  \"Schrei nach Liebe\"  von den Ärzten zu kaufen und damit ein Zeichen gegen Fremdenfeindlichkeit zu setzen. Der Song gegen Neonazis von 1993 war am Donnerstag der am meisten geladene Titel Deutschlands, wie GfK Entertainment mitteilte. Die Einnahmen wollen die Ärzte an Pro Asyl geben. In den offiziellen deutschen Charts, die neben Downloads auch physische Verkäufe berücksichtigen, landete der Song im Ermittlungszeitraum Freitag (28. 8.) bis Donnerstag (3. 9.) auf dem 12. Rang.\n\n\nUnbekannte haben in der Nacht zum Sonntag eine Skulptur des Bildhauers Anish Kapoor im Park von Schloss Versailles verschandelt. Die Täter beschmierten die Riesenplastik  \"Dirty Corner\"  mit Parolen, darunter antisemitische Beschimpfungen. Es ist bereits der zweite Angriff auf das umstrittene Kunstwerk seit Juni. Das Werk, das noch bis 1. November zu sehen ist, hatte wegen seiner sexuellen Anspielung heftige Debatten ausgelöst. Die Installation besteht aus einem 70 Meter großen Trichter aus verrostetem Stahl und Steinen. Eine Zeitung hatte Kapoor mit dem Begriff  \"Vagina der Königin\"  zitiert, später bestritt der indisch-britische Künstler mit jüdischen Vorfahren diese Beschreibung,  nannte das Werk aber  \"sehr sexuell\" .\n\n\nDer Schriftsteller Rainer Kirsch ist tot. Am Freitag ist der Lyriker, ein Vertreter der  \"Sächsischen Dichterschule\" , mit 81 Jahren in Berlin friedlich eingeschlafen, teilte der Eulenspiegel Verlag mit. Kirsch studierte Geschichte und Philosophie, arbeitete zudem in der Druck- und Chemieindustrie und in der Landwirtschaft. Trotz Schwierigkeiten mit der SED lebte er bis zum Schluss in der DDR. Zweimal wurde er aus der SED ausgeschlossen, er wurde der Universität verwiesen, und ihm wurde das Abschlussdiplom am Leipziger Literatur-Institut verweigert. Bekannt wurde Kirsch unter anderem durch die Gedichtbände  \"Gespräch mit dem Saurier\"  (1965),  \"Auszog, das Fürchten zu lernen\"  (1978) und  \"Kunst in der Mark Brandenburg\"  (1988). Daneben arbeitete er auch als Essayist, Übersetzer, Nachdichter und Kinderbuchautor. Einige Arbeiten entstanden in Zusammenarbeit mit der Lyrikerin Sarah Kirsch (1935 bis 2013), mit der er acht Jahre verheiratet war.\n\n","named_entities":[{"end":294,"text":"Deutschlands","category":"I-LOC","begin":282},{"end":317,"text":"GfK Entertainment","category":"I-ORG","begin":300},{"end":407,"text":"deutschen","category":"I-MISC","begin":398},{"end":660,"text":"Anish Kapoor","category":"I-PER","begin":648},{"end":691,"text":"Schloss Versailles","category":"I-LOC","begin":673},{"end":761,"text":"Dirty Corner","category":"I-ORG","begin":749},{"end":1215,"text":"indisch-britische","category":"I-MISC","begin":1198},{"end":1343,"text":"Rainer Kirsch","category":"I-PER","begin":1330},{"end":1426,"text":"Sächsischen Dichterschule","category":"I-ORG","begin":1401},{"end":1453,"text":"Berlin","category":"I-LOC","begin":1447},{"end":1509,"text":"Eulenspiegel Verlag","category":"I-ORG","begin":1490},{"end":1521,"text":"Kirsch","category":"I-PER","begin":1515},{"end":1670,"text":"SED","category":"I-ORG","begin":1667},{"end":1706,"text":"DDR","category":"I-LOC","begin":1703},{"end":1736,"text":"SED","category":"I-LOC","begin":1733},{"end":1835,"text":"Leipziger","category":"I-MISC","begin":1826},{"end":2039,"text":"Brandenburg","category":"I-LOC","begin":2028},{"end":2210,"text":"Sarah Kirsch","category":"I-PER","begin":2198}]}